pthat/__init__.py
pthat/pthat.py
pthat-1.0.1.dist-info/LICENSE
pthat-1.0.1.dist-info/METADATA
pthat-1.0.1.dist-info/WHEEL
pthat-1.0.1.dist-info/top_level.txt
pthat-1.0.1.dist-info/RECORD
