Metadata-Version: 2.1
Name: pthat
Version: 1.0.1
Summary: A package containing the API for the PTHat by CNC Design Limited
Home-page: https://github.com/drizztguen77/PTHat
Author: Curtis White
Author-email: drizztguen77@gmail.com
License: Apache V2
Project-URL: Documentation, https://pthat.readthedocs.io
Project-URL: Wiki, https://github.com/drizztguen77/PTHat/wiki
Project-URL: Tracker, https://github.com/drizztguen77/PTHat/issues
Keywords: pthat,api
Platform: any
Classifier: Development Status :: 3 - Alpha
Classifier: License :: OSI Approved :: Apache Software License
Classifier: Programming Language :: Python :: 3 :: Only
Classifier: Programming Language :: Python :: 3
Classifier: Programming Language :: Python :: 3.6
Classifier: Programming Language :: Python :: 3.7
Classifier: Programming Language :: Python :: 3.8
Classifier: Programming Language :: Python :: 3.9
Classifier: Operating System :: OS Independent
Classifier: Operating System :: POSIX :: Linux
Classifier: Operating System :: POSIX :: BSD :: FreeBSD
Classifier: Operating System :: Microsoft :: Windows
Classifier: Operating System :: MacOS
Classifier: Operating System :: MacOS :: MacOS X
Classifier: Environment :: MacOS X
Classifier: Environment :: Win32 (MS Windows)
Classifier: Environment :: X11 Applications
Classifier: Intended Audience :: Developers
Classifier: Intended Audience :: Information Technology
Classifier: Intended Audience :: Science/Research
Requires-Python: >=3.6
